keplergl/__init__.py
keplergl/frontend/build/asset-manifest.json
keplergl/frontend/build/favicon.ico
keplergl/frontend/build/index.html
keplergl/frontend/build/logo192.png
keplergl/frontend/build/logo512.png
keplergl/frontend/build/manifest.json
keplergl/frontend/build/robots.txt
keplergl/frontend/build/static/js/main.06b403e6.js
keplergl/frontend/build/static/js/main.06b403e6.js.LICENSE.txt
keplergl/frontend/build/static/js/main.06b403e6.js.map
keplergl/frontend/build/static/js/main.b993946a.js
keplergl/frontend/build/static/js/main.b993946a.js.LICENSE.txt
keplergl/frontend/build/static/js/main.b993946a.js.map
keplergl/frontend/build/static/js/main.f3201658.js
keplergl/frontend/build/static/js/main.f3201658.js.LICENSE.txt
keplergl/frontend/build/static/js/main.f3201658.js.map
keplergl/frontend/build/static/media/index.6126705554e95ba270e6.cjs
keplergl/frontend/build/static/media/index.6a3449ef46927f33eae3.cjs
keplergl/frontend/build/static/media/index.6a3449ef46927f33eae3.cjs.LICENSE.txt
keplergl/frontend/build/static/media/index.832b00459ef184084d04.cjs
keplergl/frontend/build/static/media/index.83a2c6e4c9c9417cd839.cjs
keplergl/frontend/build/static/media/index.97332fd7c6c843696677.cjs
keplergl/frontend/build/static/media/index.cbfcbbd045af2e854213.cjs
keplergl/frontend/build/static/media/index.de08e43f0cfc21b14308.cjs
streamlit_kepler_component-0.0.11.dist-info/LICENSE
streamlit_kepler_component-0.0.11.dist-info/METADATA
streamlit_kepler_component-0.0.11.dist-info/WHEEL
streamlit_kepler_component-0.0.11.dist-info/top_level.txt
streamlit_kepler_component-0.0.11.dist-info/RECORD
